Metadata-Version: 1.0
Name: dsnd-distributions123
Version: 0.1
Summary: Gaussian and Binomial distributions
Home-page: UNKNOWN
Author: Kausar Sayyed
Author-email: kausarsayyed.20@gmail.com
License: UNKNOWN
Platform: UNKNOWN
